{
    "azure-secrets": {
        "JsonPath": "C:\\atari-monk\\Code\\apps-data\\html-code-gen\\In\\azure-secrets.json",
        "HtmlPath": "C:\\atari-monk\\Code\\apps-data\\html-code-gen\\Out\\azure-secrets.html"
    },
    "azure-sql-db": {
        "JsonPath": "C:\\atari-monk\\Code\\apps-data\\html-code-gen\\In\\azure-sql-db.json",
        "HtmlPath": "C:\\atari-monk\\Code\\apps-data\\html-code-gen\\Out\\azure-sql-db.html"
    },
    "cpp-compiler": {
        "JsonPath": "C:\\atari-monk\\Code\\apps-data\\html-code-gen\\In\\cpp-compiler.json",
        "HtmlPath": "C:\\atari-monk\\Code\\apps-data\\html-code-gen\\Out\\cpp-compiler.html"
    },
    "csharp-job-test": {
        "JsonPath": "C:\\atari-monk\\Code\\apps-data\\html-code-gen\\In\\csharp-job-test.json",
        "HtmlPath": "C:\\atari-monk\\Code\\apps-data\\html-code-gen\\Out\\csharp-job-test.html"
    },
    "html-beginner-tutorial": {
        "JsonPath": "C:\\atari-monk\\Code\\apps-data\\html-code-gen\\In\\html-beginner-tutorial.json",
        "HtmlPath": "C:\\atari-monk\\Code\\apps-data\\html-code-gen\\Out\\html-beginner-tutorial.html"
    },
    "identity-db-lib": {
        "JsonPath": "C:\\atari-monk\\Code\\apps-data\\html-code-gen\\In\\identity-db-lib.json",
        "HtmlPath": "C:\\atari-monk\\Code\\apps-data\\html-code-gen\\Out\\identity-db-lib.html"
    },
    "identity-web-app": {
        "JsonPath": "C:\\atari-monk\\Code\\apps-data\\html-code-gen\\In\\identity-web-app.json",
        "HtmlPath": "C:\\atari-monk\\Code\\apps-data\\html-code-gen\\Out\\identity-web-app.html"
    },
    "javascript-beginner-game": {
        "JsonPath": "C:\\atari-monk\\Code\\apps-data\\html-code-gen\\In\\javascript-beginner-game.json",
        "HtmlPath": "C:\\atari-monk\\Code\\apps-data\\html-code-gen\\Out\\javascript-beginner-game.html"
    },
    "javascript-course-part1": {
        "JsonPath": "C:\\atari-monk\\Code\\apps-data\\html-code-gen\\In\\javascript-course-part1.json",
        "HtmlPath": "C:\\atari-monk\\Code\\apps-data\\html-code-gen\\Out\\javascript-course-part1.html"
    },
    "javascript-course-part2": {
        "JsonPath": "C:\\atari-monk\\Code\\apps-data\\html-code-gen\\In\\javascript-course-part2.json",
        "HtmlPath": "C:\\atari-monk\\Code\\apps-data\\html-code-gen\\Out\\javascript-course-part2.html"
    },
    "javascript-course-part3": {
        "JsonPath": "C:\\atari-monk\\Code\\apps-data\\html-code-gen\\In\\javascript-course-part3.json",
        "HtmlPath": "C:\\atari-monk\\Code\\apps-data\\html-code-gen\\Out\\javascript-course-part3.html"
    },
    "javascript-course-part4": {
        "JsonPath": "C:\\atari-monk\\Code\\apps-data\\html-code-gen\\In\\javascript-course-part4.json",
        "HtmlPath": "C:\\atari-monk\\Code\\apps-data\\html-code-gen\\Out\\javascript-course-part4.html"
    },
    "javascript-course-part5": {
        "JsonPath": "C:\\atari-monk\\Code\\apps-data\\html-code-gen\\In\\javascript-course-part5.json",
        "HtmlPath": "C:\\atari-monk\\Code\\apps-data\\html-code-gen\\Out\\javascript-course-part5.html"
    },
    "javascript-course-part6-7": {
        "JsonPath": "C:\\atari-monk\\Code\\apps-data\\html-code-gen\\In\\javascript-course-part6-7.json",
        "HtmlPath": "C:\\atari-monk\\Code\\apps-data\\html-code-gen\\Out\\javascript-course-part6-7.html"
    },
    "javascript-course-part8-11": {
        "JsonPath": "C:\\atari-monk\\Code\\apps-data\\html-code-gen\\In\\javascript-course-part8-11.json",
        "HtmlPath": "C:\\atari-monk\\Code\\apps-data\\html-code-gen\\Out\\javascript-course-part8-11.html"
    },
    "javascript-course-part12": {
        "JsonPath": "C:\\atari-monk\\Code\\apps-data\\html-code-gen\\In\\javascript-course-part12.json",
        "HtmlPath": "C:\\atari-monk\\Code\\apps-data\\html-code-gen\\Out\\javascript-course-part12.html"
    },
    "new-github-repo": {
        "JsonPath": "C:\\atari-monk\\Code\\apps-data\\html-code-gen\\In\\new-github-repo.json",
        "HtmlPath": "C:\\atari-monk\\Code\\apps-data\\html-code-gen\\Out\\new-github-repo.html"
    },
    "node-js-azure": {
        "JsonPath": "C:\\atari-monk\\Code\\apps-data\\html-code-gen\\In\\node-js-azure.json",
        "HtmlPath": "C:\\atari-monk\\Code\\apps-data\\html-code-gen\\Out\\node-js-azure.html"
    },
    "nuget": {
        "JsonPath": "C:\\atari-monk\\Code\\apps-data\\html-code-gen\\In\\nuget.json",
        "HtmlPath": "C:\\atari-monk\\Code\\apps-data\\html-code-gen\\Out\\nuget.html"
    },
    "path-sys-var": {
        "JsonPath": "C:\\atari-monk\\Code\\apps-data\\html-code-gen\\In\\path-sys-var.json",
        "HtmlPath": "C:\\atari-monk\\Code\\apps-data\\html-code-gen\\Out\\path-sys-var.html"
    },
    "pong-dev-notes": {
        "JsonPath": "C:\\atari-monk\\Code\\apps-data\\html-code-gen\\In\\pong-dev-notes.json",
        "HtmlPath": "C:\\atari-monk\\Code\\apps-data\\html-code-gen\\Out\\pong-dev-notes.html"
    },
    "python-beginner-tutorial": {
        "JsonPath": "C:\\atari-monk\\Code\\apps-data\\html-code-gen\\In\\python-beginner-tutorial.json",
        "HtmlPath": "C:\\atari-monk\\Code\\apps-data\\html-code-gen\\Out\\python-beginner-tutorial.html"
    },
    "remove-background": {
        "JsonPath": "C:\\atari-monk\\Code\\apps-data\\html-code-gen\\In\\remove-background.json",
        "HtmlPath": "C:\\atari-monk\\Code\\apps-data\\html-code-gen\\Out\\remove-background.html"
    },
    "schema": {
        "JsonPath": "C:\\atari-monk\\Code\\apps-data\\html-code-gen\\In\\schema.json",
        "HtmlPath": "C:\\atari-monk\\Code\\apps-data\\html-code-gen\\Out\\schema.html"
    },
    "secrets": {
        "JsonPath": "C:\\atari-monk\\Code\\apps-data\\html-code-gen\\In\\secrets.json",
        "HtmlPath": "C:\\atari-monk\\Code\\apps-data\\html-code-gen\\Out\\secrets.html"
    },
    "socket-io-azure": {
        "JsonPath": "C:\\atari-monk\\Code\\apps-data\\html-code-gen\\In\\socket-io-azure.json",
        "HtmlPath": "C:\\atari-monk\\Code\\apps-data\\html-code-gen\\Out\\socket-io-azure.html"
    },
    "sql": {
        "JsonPath": "C:\\atari-monk\\Code\\apps-data\\html-code-gen\\In\\sql.json",
        "HtmlPath": "C:\\atari-monk\\Code\\apps-data\\html-code-gen\\Out\\sql.html"
    },
    "ssms-azure": {
        "JsonPath": "C:\\atari-monk\\Code\\apps-data\\html-code-gen\\In\\ssms-azure.json",
        "HtmlPath": "C:\\atari-monk\\Code\\apps-data\\html-code-gen\\Out\\ssms-azure.html"
    },
    "stream-video": {
        "JsonPath": "C:\\atari-monk\\Code\\apps-data\\html-code-gen\\In\\stream-video.json",
        "HtmlPath": "C:\\atari-monk\\Code\\apps-data\\html-code-gen\\Out\\stream-video.html"
    },
    "todo-app-azure": {
        "JsonPath": "C:\\atari-monk\\Code\\apps-data\\html-code-gen\\In\\todo-app-azure.json",
        "HtmlPath": "C:\\atari-monk\\Code\\apps-data\\html-code-gen\\Out\\todo-app-azure.html"
    },
    "tools": {
        "JsonPath": "C:\\atari-monk\\Code\\apps-data\\html-code-gen\\In\\tools.json",
        "HtmlPath": "C:\\atari-monk\\Code\\apps-data\\html-code-gen\\Out\\tools.html"
    },
    "voting-app-azure": {
        "JsonPath": "C:\\atari-monk\\Code\\apps-data\\html-code-gen\\In\\voting-app-azure.json",
        "HtmlPath": "C:\\atari-monk\\Code\\apps-data\\html-code-gen\\Out\\voting-app-azure.html"
    },
    "vscode": {
        "JsonPath": "C:\\atari-monk\\Code\\apps-data\\html-code-gen\\In\\vscode.json",
        "HtmlPath": "C:\\atari-monk\\Code\\apps-data\\html-code-gen\\Out\\vscode.html"
    },
    "web-app-dotnet-upgrade": {
        "JsonPath": "C:\\atari-monk\\Code\\apps-data\\html-code-gen\\In\\web-app-dotnet-upgrade.json",
        "HtmlPath": "C:\\atari-monk\\Code\\apps-data\\html-code-gen\\Out\\web-app-dotnet-upgrade.html"
    }
}
